README.md
setup.py
alpha_vantage_proxy/__init__.py
alpha_vantage_proxy/models.py
alpha_vantage_proxy/timeseries.py
alpha_vantage_proxy.egg-info/PKG-INFO
alpha_vantage_proxy.egg-info/SOURCES.txt
alpha_vantage_proxy.egg-info/dependency_links.txt
alpha_vantage_proxy.egg-info/not-zip-safe
alpha_vantage_proxy.egg-info/top_level.txt