Metadata-Version: 1.0
Name: alpha-vantage-proxy
Version: 0.0.2
Summary: A plugin to interface with alphavantage api
Home-page: UNKNOWN
Author: Kaleb Burd
Author-email: kalebmburd@gmail.com
License: MIT
Platform: UNKNOWN
